{
  "requestedWord": "kriips",
  "estonianWord": "kriips",
  "searchResult": [
    {
      "wordClasses": [
        "noomen"
      ],
      "wordForms": [
        {
          "inflectionType": "22e",
          "code": "SgN",
          "morphValue": "ainsuse nimetav",
          "value": "kriips"
        },
        {
          "inflectionType": "22e",
          "code": "SgG",
          "morphValue": "ainsuse omastav",
          "value": "kriipsu"
        },
        {
          "inflectionType": "22e",
          "code": "SgP",
          "morphValue": "ainsuse osastav",
          "value": "kriipsu"
        },
        {
          "inflectionType": "22e",
          "code": "SgAdt",
          "morphValue": "ainsuse suunduv e lühike sisseütlev",
          "value": "kriipsu"
        },
        {
          "inflectionType": "22e",
          "code": "SgIll",
          "morphValue": "ainsuse sisseütlev",
          "value": "kriipsusse"
        },
        {
          "inflectionType": "22e",
          "code": "SgIn",
          "morphValue": "ainsuse seesütlev",
          "value": "kriipsus"
        },
        {
          "inflectionType": "22e",
          "code": "SgEl",
          "morphValue": "ainsuse seestütlev",
          "value": "kriipsust"
        },
        {
          "inflectionType": "22e",
          "code": "SgAll",
          "morphValue": "ainsuse alaleütlev",
          "value": "kriipsule"
        },
        {
          "inflectionType": "22e",
          "code": "SgAd",
          "morphValue": "ainsuse alalütlev",
          "value": "kriipsul"
        },
        {
          "inflectionType": "22e",
          "code": "SgAbl",
          "morphValue": "ainsuse alaltütlev",
          "value": "kriipsult"
        },
        {
          "inflectionType": "22e",
          "code": "SgTr",
          "morphValue": "ainsuse saav",
          "value": "kriipsuks"
        },
        {
          "inflectionType": "22e",
          "code": "SgTer",
          "morphValue": "ainsuse rajav",
          "value": "kriipsuni"
        },
        {
          "inflectionType": "22e",
          "code": "SgEs",
          "morphValue": "ainsuse olev",
          "value": "kriipsuna"
        },
        {
          "inflectionType": "22e",
          "code": "SgAb",
          "morphValue": "ainsuse ilmaütlev",
          "value": "kriipsuta"
        },
        {
          "inflectionType": "22e",
          "code": "SgKom",
          "morphValue": "ainsuse kaasaütlev",
          "value": "kriipsuga"
        },
        {
          "inflectionType": "22e",
          "code": "PlN",
          "morphValue": "mitmuse nimetav",
          "value": "kriipsud"
        },
        {
          "inflectionType": "22e",
          "code": "PlG",
          "morphValue": "mitmuse omastav",
          "value": "kriipsude"
        },
        {
          "inflectionType": "22e",
          "code": "PlP",
          "morphValue": "mitmuse osastav",
          "value": "kriipse,kriipsusid"
        },
        {
          "inflectionType": "22e",
          "code": "PlIll",
          "morphValue": "mitmuse sisseütlev",
          "value": "kriipsudesse,kriipsesse"
        },
        {
          "inflectionType": "22e",
          "code": "PlIn",
          "morphValue": "mitmuse seesütlev",
          "value": "kriipsudes,kriipses"
        },
        {
          "inflectionType": "22e",
          "code": "PlEl",
          "morphValue": "mitmuse seestütlev",
          "value": "kriipsudest,kriipsest"
        },
        {
          "inflectionType": "22e",
          "code": "PlAll",
          "morphValue": "mitmuse alaleütlev",
          "value": "kriipsudele,kriipsele"
        },
        {
          "inflectionType": "22e",
          "code": "PlAd",
          "morphValue": "mitmuse alalütlev",
          "value": "kriipsudel,kriipsel"
        },
        {
          "inflectionType": "22e",
          "code": "PlAbl",
          "morphValue": "mitmuse alaltütlev",
          "value": "kriipsudelt,kriipselt"
        },
        {
          "inflectionType": "22e",
          "code": "PlTr",
          "morphValue": "mitmuse saav",
          "value": "kriipsudeks,kriipseks"
        },
        {
          "inflectionType": "22e",
          "code": "PlTer",
          "morphValue": "mitmuse rajav",
          "value": "kriipsudeni"
        },
        {
          "inflectionType": "22e",
          "code": "PlEs",
          "morphValue": "mitmuse olev",
          "value": "kriipsudena"
        },
        {
          "inflectionType": "22e",
          "code": "PlAb",
          "morphValue": "mitmuse ilmaütlev",
          "value": "kriipsudeta"
        },
        {
          "inflectionType": "22e",
          "code": "PlKom",
          "morphValue": "mitmuse kaasaütlev",
          "value": "kriipsudega"
        }
      ],
      "meanings": [
        {
          "definition": "pikk ja peenike märk millegi pinnal, mis eraldab, piirab või tähistab midagi,pikk ja peenike märk millegi pinnal, mis näeb välja selline: –––",
          "partOfSpeech": [
            {
              "code": "s",
              "value": "nimisõna, substantiiv"
            }
          ],
          "examples": [
            "Kriipsud ja kuupäevad uksepiidal märkisid su kasvamist.",
            "Mõnikord veab ta pikki ja sirgeid kriipse paberile, teinekord teeb hoopis hästi palju hästi pisikesi täppe.",
            "Järgmise põlvkonna käes peremärk muutus: isa peremärgile lisati mingi uus element, näiteks kriips või ring.",
            "Tüdruk pigistas oma suu kriipsuks kinni ega öelnud sõnagi."
          ],
          "synonyms": [
            "joon",
            "jutt",
            "triip,viir,viirg,vööt",
            "niit",
            "kriipsuke,kriipsukene",
            "riba"
          ],
          "translations": {
            "fra": [
              {
                "words": "ligne",
                "weight": 1
              },
              {
                "words": "rayure",
                "weight": 0.9
              }
            ],
            "rus": [
              {
                "words": "линия",
                "weight": 1
              },
              {
                "words": "черта",
                "weight": 1
              },
              {
                "words": "штрих",
                "weight": 1
              },
              {
                "words": "полоса",
                "weight": 1
              },
              {
                "words": "полоска",
                "weight": 1
              },
              {
                "words": "чёрточка",
                "weight": 1
              },
              {
                "words": "линия,полоса,черта,штрих,полоска",
                "weight": 0.9
              },
              {
                "words": "чёрточка",
                "weight": 0.692
              },
              {
                "words": "полоса",
                "weight": 0.75
              }
            ],
            "ukr": [
              {
                "words": "лінія",
                "weight": 1
              },
              {
                "words": "риска",
                "weight": 1
              },
              {
                "words": "риса",
                "weight": 1
              },
              {
                "words": "смуга",
                "weight": 1
              },
              {
                "words": "смужка",
                "weight": 1
              },
              {
                "words": "штрих",
                "weight": 1
              },
              {
                "words": "смуга,смужка",
                "weight": 0.9
              }
            ],
            "eng": [
              {
                "words": "stripe",
                "weight": 0.9
              }
            ]
          }
        },
        {
          "definition": "mingi mõõduriista skaalal sel viisil tähistatud ühik (nt termomeetril)",
          "partOfSpeech": [
            {
              "code": "s",
              "value": "nimisõna, substantiiv"
            }
          ],
          "examples": [
            "Palavik langes paari kriipsu võrra."
          ],
          "synonyms": [
            "pügal",
            "mõõdukriips"
          ],
          "translations": {
            "rus": [
              {
                "words": "деление",
                "weight": 1
              },
              {
                "words": "градус",
                "weight": 0.7
              },
              {
                "words": "отметка на измерительной шкале,деление",
                "weight": 0.7
              }
            ]
          }
        }
      ],
      "similarWords": [
        "pügal",
        "poolituskriips",
        "mõõdukriips",
        "jaotuskriips",
        "joon",
        "pilbas",
        "niit",
        "kiitsakas",
        "kõrendik",
        "kõrend",
        "jutt",
        "kõhn",
        "kriipsujuku",
        "silguniisk",
        "kilu",
        "kondibukett",
        "kraaps",
        "viir",
        "viirg",
        "rivi",
        "kriipsutama",
        "mõttekriips",
        "allakriipsutus",
        "kriipsuke",
        "sidekriips",
        "kaldkriips",
        "püstkriips",
        "piibuora",
        "surmavari",
        "sorakas",
        "kiisk",
        "kärbis",
        "inimvari",
        "niit",
        "nahk",
        "niru",
        "kont",
        "kont",
        "jutt",
        "rootsik",
        "roots",
        "roots",
        "piitsavars",
        "luukarnits",
        "kondikubu",
        "nääps",
        "piibuork",
        "surmakutsar",
        "kraaps",
        "varjukuju",
        "vöönd",
        "suund"
      ]
    },
    {
      "wordClasses": [
        "muutumatu"
      ],
      "wordForms": [
        {
          "inflectionType": "41",
          "code": "ID",
          "morphValue": "muutumatu sõna (indekl)",
          "value": "kriips"
        }
      ],
      "meanings": [
        {
          "definition": "annab edasi kraapimise, (mingi esemega) kriimustamise teravat heli",
          "partOfSpeech": [
            {
              "code": "adv",
              "value": "määrsõna, adverb"
            },
            {
              "code": "interj",
              "value": "hüüdsõna, interjektsioon"
            }
          ],
          "examples": [
            "Teet tõmbas pliiatsiga kriips ja kriips paberile jutte."
          ],
          "synonyms": [
            "kraaps,kriips-kraaps"
          ],
          "translations": {
            "rus": [
              {
                "words": "скрип-скрип",
                "weight": 1
              },
              {
                "words": "шкряб-шкряб",
                "weight": 0.9
              }
            ]
          }
        }
      ],
      "similarWords": [
        "piibuora",
        "surmavari",
        "joon",
        "pilbas",
        "sorakas",
        "kiisk",
        "kärbis",
        "inimvari",
        "niit",
        "niit",
        "kiitsakas",
        "kõrendik",
        "kõrend",
        "nahk",
        "niru",
        "kont",
        "kont",
        "jutt",
        "jutt",
        "kõhn",
        "rootsik",
        "roots",
        "roots",
        "piitsavars",
        "luukarnits",
        "kondikubu",
        "nääps",
        "kriipsujuku",
        "piibuork",
        "surmakutsar",
        "silguniisk",
        "kilu",
        "kondibukett",
        "kraaps",
        "kraaps",
        "varjukuju",
        "vöönd",
        "viir",
        "viirg",
        "suund",
        "rivi",
        "kriipsutama",
        "mõttekriips",
        "allakriipsutus",
        "kriipsuke",
        "sidekriips",
        "kaldkriips",
        "püstkriips"
      ]
    }
  ],
  "translations": [
    {
      "from": "et",
      "to": "en",
      "input": "kriips",
      "translations": [
        "dah (morsekoodis)",
        "dash",
        "iota (tühine kogus)"
      ]
    }
  ]
}