{
  "requestedWord": "marginaalne",
  "estonianWord": "marginaalne",
  "searchResult": [
    {
      "wordClasses": [
        "noomen"
      ],
      "wordForms": [
        {
          "inflectionType": "02",
          "code": "SgN",
          "morphValue": "ainsuse nimetav",
          "value": "marginaalne"
        },
        {
          "inflectionType": "02",
          "code": "SgG",
          "morphValue": "ainsuse omastav",
          "value": "marginaalse"
        },
        {
          "inflectionType": "02",
          "code": "SgP",
          "morphValue": "ainsuse osastav",
          "value": "marginaalset"
        },
        {
          "inflectionType": "02",
          "code": "SgAdt",
          "morphValue": "ainsuse suunduv e lühike sisseütlev",
          "value": "-"
        },
        {
          "inflectionType": "02",
          "code": "SgIll",
          "morphValue": "ainsuse sisseütlev",
          "value": "marginaalsesse"
        },
        {
          "inflectionType": "02",
          "code": "SgIn",
          "morphValue": "ainsuse seesütlev",
          "value": "marginaalses"
        },
        {
          "inflectionType": "02",
          "code": "SgEl",
          "morphValue": "ainsuse seestütlev",
          "value": "marginaalsest"
        },
        {
          "inflectionType": "02",
          "code": "SgAll",
          "morphValue": "ainsuse alaleütlev",
          "value": "marginaalsele"
        },
        {
          "inflectionType": "02",
          "code": "SgAd",
          "morphValue": "ainsuse alalütlev",
          "value": "marginaalsel"
        },
        {
          "inflectionType": "02",
          "code": "SgAbl",
          "morphValue": "ainsuse alaltütlev",
          "value": "marginaalselt"
        },
        {
          "inflectionType": "02",
          "code": "SgTr",
          "morphValue": "ainsuse saav",
          "value": "marginaalseks"
        },
        {
          "inflectionType": "02",
          "code": "SgTer",
          "morphValue": "ainsuse rajav",
          "value": "marginaalseni"
        },
        {
          "inflectionType": "02",
          "code": "SgEs",
          "morphValue": "ainsuse olev",
          "value": "marginaalsena"
        },
        {
          "inflectionType": "02",
          "code": "SgAb",
          "morphValue": "ainsuse ilmaütlev",
          "value": "marginaalseta"
        },
        {
          "inflectionType": "02",
          "code": "SgKom",
          "morphValue": "ainsuse kaasaütlev",
          "value": "marginaalsega"
        },
        {
          "inflectionType": "02",
          "code": "PlN",
          "morphValue": "mitmuse nimetav",
          "value": "marginaalsed"
        },
        {
          "inflectionType": "02",
          "code": "PlG",
          "morphValue": "mitmuse omastav",
          "value": "marginaalsete"
        },
        {
          "inflectionType": "02",
          "code": "PlP",
          "morphValue": "mitmuse osastav",
          "value": "marginaalseid"
        },
        {
          "inflectionType": "02",
          "code": "PlIll",
          "morphValue": "mitmuse sisseütlev",
          "value": "marginaalsetesse,marginaalseisse"
        },
        {
          "inflectionType": "02",
          "code": "PlIn",
          "morphValue": "mitmuse seesütlev",
          "value": "marginaalsetes,marginaalseis"
        },
        {
          "inflectionType": "02",
          "code": "PlEl",
          "morphValue": "mitmuse seestütlev",
          "value": "marginaalsetest,marginaalseist"
        },
        {
          "inflectionType": "02",
          "code": "PlAll",
          "morphValue": "mitmuse alaleütlev",
          "value": "marginaalsetele,marginaalseile"
        },
        {
          "inflectionType": "02",
          "code": "PlAd",
          "morphValue": "mitmuse alalütlev",
          "value": "marginaalsetel,marginaalseil"
        },
        {
          "inflectionType": "02",
          "code": "PlAbl",
          "morphValue": "mitmuse alaltütlev",
          "value": "marginaalsetelt,marginaalseilt"
        },
        {
          "inflectionType": "02",
          "code": "PlTr",
          "morphValue": "mitmuse saav",
          "value": "marginaalseteks,marginaalseiks"
        },
        {
          "inflectionType": "02",
          "code": "PlTer",
          "morphValue": "mitmuse rajav",
          "value": "marginaalseteni"
        },
        {
          "inflectionType": "02",
          "code": "PlEs",
          "morphValue": "mitmuse olev",
          "value": "marginaalsetena"
        },
        {
          "inflectionType": "02",
          "code": "PlAb",
          "morphValue": "mitmuse ilmaütlev",
          "value": "marginaalseteta"
        },
        {
          "inflectionType": "02",
          "code": "PlKom",
          "morphValue": "mitmuse kaasaütlev",
          "value": "marginaalsetega"
        }
      ],
      "meanings": [
        {
          "definition": "üsna ebaoluline, (tähtsuse poolest) kõrvaline,(arvu, suuruse, hulga poolest) tühine",
          "partOfSpeech": [
            {
              "code": "adj",
              "value": "omadussõna, adjektiiv"
            }
          ],
          "examples": [
            "Autori kommentaar on mõistmise seisukohalt marginaalne.",
            "Määruse mõju kaubandusele jääb marginaalseks.",
            "Remondikulud olid üsna marginaalsed."
          ],
          "synonyms": [
            "marginaal",
            "tähtsusetu,vähetähtis,ebaoluline",
            "kõrvaline,sekundaarne,teisejärguline,teisene",
            "väheoluline",
            "tühine"
          ],
          "translations": {
            "rus": [
              {
                "words": "маргинальный",
                "weight": 1
              },
              {
                "words": "проходной,пустой,ничтожный,несущественный,неважный,малосущественный,незначительный,малозначительный,третьестепенный,второстепенный,маловажный,пустяковый",
                "weight": 0.7
              },
              {
                "words": "несущественный,побочный,второстепенный,вторичный,второочередной,маловажный,менее важный",
                "weight": 0.7
              },
              {
                "words": "малосущественный,маловажный",
                "weight": 0.7
              },
              {
                "words": "несущественный,неважный,незначительный,малозначительный,маловажный,мелочный,пустячный,пустяковый,ничтожный",
                "weight": 0.7
              }
            ],
            "fra": [
              {
                "words": "secondaire,sans importance,peu important,insignifiant",
                "weight": 0.7
              }
            ],
            "ukr": [
              {
                "words": "неважливий,малозначний,незначущий",
                "weight": 0.7
              }
            ],
            "eng": [
              {
                "words": "irrelevant,insignificant,unimportant",
                "weight": 0.7
              }
            ]
          }
        },
        {
          "definition": "(asukohalt, kuuluvuselt) ääre-, piirialale jääv",
          "partOfSpeech": [
            {
              "code": "adj",
              "value": "omadussõna, adjektiiv"
            }
          ],
          "examples": [
            "Marginaalse paiknemisega ökosüsteemid on ebastabiilsed."
          ],
          "synonyms": [
            "veermine",
            "servmine",
            "äärmine"
          ],
          "translations": {
            "rus": [
              {
                "words": "маргинальный",
                "weight": 1
              },
              {
                "words": "крайний",
                "weight": 0.7
              },
              {
                "words": "крайний",
                "weight": 0.9
              },
              {
                "words": "крайний,с краю",
                "weight": 0.9
              }
            ]
          }
        }
      ],
      "similarWords": [
        "tühine",
        "ebaoluline",
        "väheoluline",
        "kõrvaline",
        "äärmine",
        "servmine",
        "veermine",
        "marginaal",
        "marginaliseerimine",
        "marginaliseerumine",
        "marginaalsus",
        "intressimarginaal"
      ]
    }
  ],
  "translations": [
    {
      "from": "et",
      "to": "en",
      "input": "marginaalne",
      "translations": []
    }
  ]
}