{
  "requestedWord": "loetelu",
  "estonianWord": "loetelu",
  "searchResult": [
    {
      "wordClasses": [
        "noomen"
      ],
      "wordForms": [
        {
          "inflectionType": "17",
          "code": "SgN",
          "morphValue": "ainsuse nimetav",
          "value": "loetelu"
        },
        {
          "inflectionType": "17",
          "code": "SgG",
          "morphValue": "ainsuse omastav",
          "value": "loetelu"
        },
        {
          "inflectionType": "17",
          "code": "SgP",
          "morphValue": "ainsuse osastav",
          "value": "loetelu"
        },
        {
          "inflectionType": "17",
          "code": "SgAdt",
          "morphValue": "ainsuse suunduv e lühike sisseütlev",
          "value": "loetellu"
        },
        {
          "inflectionType": "17",
          "code": "SgIll",
          "morphValue": "ainsuse sisseütlev",
          "value": "loetelusse"
        },
        {
          "inflectionType": "17",
          "code": "SgIn",
          "morphValue": "ainsuse seesütlev",
          "value": "loetelus"
        },
        {
          "inflectionType": "17",
          "code": "SgEl",
          "morphValue": "ainsuse seestütlev",
          "value": "loetelust"
        },
        {
          "inflectionType": "17",
          "code": "SgAll",
          "morphValue": "ainsuse alaleütlev",
          "value": "loetelule"
        },
        {
          "inflectionType": "17",
          "code": "SgAd",
          "morphValue": "ainsuse alalütlev",
          "value": "loetelul"
        },
        {
          "inflectionType": "17",
          "code": "SgAbl",
          "morphValue": "ainsuse alaltütlev",
          "value": "loetelult"
        },
        {
          "inflectionType": "17",
          "code": "SgTr",
          "morphValue": "ainsuse saav",
          "value": "loeteluks"
        },
        {
          "inflectionType": "17",
          "code": "SgTer",
          "morphValue": "ainsuse rajav",
          "value": "loeteluni"
        },
        {
          "inflectionType": "17",
          "code": "SgEs",
          "morphValue": "ainsuse olev",
          "value": "loeteluna"
        },
        {
          "inflectionType": "17",
          "code": "SgAb",
          "morphValue": "ainsuse ilmaütlev",
          "value": "loeteluta"
        },
        {
          "inflectionType": "17",
          "code": "SgKom",
          "morphValue": "ainsuse kaasaütlev",
          "value": "loeteluga"
        },
        {
          "inflectionType": "17",
          "code": "PlN",
          "morphValue": "mitmuse nimetav",
          "value": "loetelud"
        },
        {
          "inflectionType": "17",
          "code": "PlG",
          "morphValue": "mitmuse omastav",
          "value": "loetelude"
        },
        {
          "inflectionType": "17",
          "code": "PlP",
          "morphValue": "mitmuse osastav",
          "value": "loetelusid"
        },
        {
          "inflectionType": "17",
          "code": "PlIll",
          "morphValue": "mitmuse sisseütlev",
          "value": "loeteludesse"
        },
        {
          "inflectionType": "17",
          "code": "PlIn",
          "morphValue": "mitmuse seesütlev",
          "value": "loeteludes"
        },
        {
          "inflectionType": "17",
          "code": "PlEl",
          "morphValue": "mitmuse seestütlev",
          "value": "loeteludest"
        },
        {
          "inflectionType": "17",
          "code": "PlAll",
          "morphValue": "mitmuse alaleütlev",
          "value": "loeteludele"
        },
        {
          "inflectionType": "17",
          "code": "PlAd",
          "morphValue": "mitmuse alalütlev",
          "value": "loeteludel"
        },
        {
          "inflectionType": "17",
          "code": "PlAbl",
          "morphValue": "mitmuse alaltütlev",
          "value": "loeteludelt"
        },
        {
          "inflectionType": "17",
          "code": "PlTr",
          "morphValue": "mitmuse saav",
          "value": "loeteludeks"
        },
        {
          "inflectionType": "17",
          "code": "PlTer",
          "morphValue": "mitmuse rajav",
          "value": "loeteludeni"
        },
        {
          "inflectionType": "17",
          "code": "PlEs",
          "morphValue": "mitmuse olev",
          "value": "loeteludena"
        },
        {
          "inflectionType": "17",
          "code": "PlAb",
          "morphValue": "mitmuse ilmaütlev",
          "value": "loeteludeta"
        },
        {
          "inflectionType": "17",
          "code": "PlKom",
          "morphValue": "mitmuse kaasaütlev",
          "value": "loeteludega"
        }
      ],
      "meanings": [
        {
          "definition": "loetlemine, samalaadsete asjade üksteise järel nimetamine,üksteise järel nimetatud asjad vms (ka kirjaliku kogumina),üksteise järel kirja pandud asjad, näiteks mingid ülesanded või kaubad,nimekiri",
          "partOfSpeech": [
            {
              "code": "s",
              "value": "nimisõna, substantiiv"
            }
          ],
          "examples": [
            "Üksikasjalisem loetelu läheks pikaks.",
            "Juba kirjanduse loetelu annab tunnistust autori laiast haardest.",
            "Uurimuse lõppu tuleb lisada kasutatud kirjanduse loetelu."
          ],
          "synonyms": [
            "nimekiri,nimestik,nimistu",
            "loend",
            "üleslugemine,loetlus,loetlemine",
            "nimeloend",
            "register",
            "üleskirjutamine",
            "üleskirjutus",
            "indeks,register"
          ],
          "translations": {
            "fra": [
              {
                "words": "énumération",
                "weight": 1
              },
              {
                "words": "liste",
                "weight": 1
              },
              {
                "words": "liste",
                "weight": 0.9
              },
              {
                "words": "liste",
                "weight": 0.822
              }
            ],
            "rus": [
              {
                "words": "перечень",
                "weight": 1
              },
              {
                "words": "список",
                "weight": 1
              },
              {
                "words": "перечисление",
                "weight": 1
              },
              {
                "words": "указатель",
                "weight": 1
              },
              {
                "words": "поимённый список,список,перечень,именной список,опись",
                "weight": 0.9
              },
              {
                "words": "список,перечень,указатель,роспись",
                "weight": 0.822
              },
              {
                "words": "счёт,перечисление,перечень,расчёт",
                "weight": 0.75
              },
              {
                "words": "именной указатель",
                "weight": 0.566
              },
              {
                "words": "реестр,регистр",
                "weight": 0.9
              },
              {
                "words": "записывание,запись",
                "weight": 0.75
              },
              {
                "words": "запись,принятие на учёт,учёт,регистрирование,записывание",
                "weight": 0.9
              },
              {
                "words": "индекс,указатель",
                "weight": 0.9
              }
            ],
            "ukr": [
              {
                "words": "перелік",
                "weight": 1
              },
              {
                "words": "список",
                "weight": 1
              },
              {
                "words": "список",
                "weight": 0.9
              },
              {
                "words": "список,перелік",
                "weight": 0.822
              }
            ]
          }
        }
      ],
      "similarWords": [
        "loend",
        "nimistu",
        "nimestik",
        "nimekiri",
        "register",
        "nomenklatuur",
        "konkordants",
        "indeks",
        "loetlus",
        "üleskirjutamine",
        "üleskirjutus",
        "mõõtur",
        "regulaator",
        "sõnaloend",
        "poenimekiri",
        "nimeloend",
        "bibliograafialoetelu",
        "täpploend"
      ]
    }
  ],
  "translations": [
    {
      "from": "et",
      "to": "en",
      "input": "loetelu",
      "translations": [
        "enumeration",
        "listing"
      ]
    }
  ]
}