{
  "requestedWord": "selgroog",
  "estonianWord": "selgroog",
  "searchResult": [
    {
      "wordClasses": [
        "noomen"
      ],
      "wordForms": [
        {
          "inflectionType": "22e",
          "code": "SgN",
          "morphValue": "ainsuse nimetav",
          "value": "selgroog"
        },
        {
          "inflectionType": "22e",
          "code": "SgG",
          "morphValue": "ainsuse omastav",
          "value": "selgroo"
        },
        {
          "inflectionType": "22e",
          "code": "SgP",
          "morphValue": "ainsuse osastav",
          "value": "selgroogu"
        },
        {
          "inflectionType": "22e",
          "code": "SgAdt",
          "morphValue": "ainsuse suunduv e lühike sisseütlev",
          "value": "selgroogu"
        },
        {
          "inflectionType": "22e",
          "code": "SgIll",
          "morphValue": "ainsuse sisseütlev",
          "value": "selgroosse"
        },
        {
          "inflectionType": "22e",
          "code": "SgIn",
          "morphValue": "ainsuse seesütlev",
          "value": "selgroos"
        },
        {
          "inflectionType": "22e",
          "code": "SgEl",
          "morphValue": "ainsuse seestütlev",
          "value": "selgroost"
        },
        {
          "inflectionType": "22e",
          "code": "SgAll",
          "morphValue": "ainsuse alaleütlev",
          "value": "selgroole"
        },
        {
          "inflectionType": "22e",
          "code": "SgAd",
          "morphValue": "ainsuse alalütlev",
          "value": "selgrool"
        },
        {
          "inflectionType": "22e",
          "code": "SgAbl",
          "morphValue": "ainsuse alaltütlev",
          "value": "selgroolt"
        },
        {
          "inflectionType": "22e",
          "code": "SgTr",
          "morphValue": "ainsuse saav",
          "value": "selgrooks"
        },
        {
          "inflectionType": "22e",
          "code": "SgTer",
          "morphValue": "ainsuse rajav",
          "value": "selgrooni"
        },
        {
          "inflectionType": "22e",
          "code": "SgEs",
          "morphValue": "ainsuse olev",
          "value": "selgroona"
        },
        {
          "inflectionType": "22e",
          "code": "SgAb",
          "morphValue": "ainsuse ilmaütlev",
          "value": "selgroota"
        },
        {
          "inflectionType": "22e",
          "code": "SgKom",
          "morphValue": "ainsuse kaasaütlev",
          "value": "selgrooga"
        },
        {
          "inflectionType": "22e",
          "code": "PlN",
          "morphValue": "mitmuse nimetav",
          "value": "selgrood"
        },
        {
          "inflectionType": "22e",
          "code": "PlG",
          "morphValue": "mitmuse omastav",
          "value": "selgroogude"
        },
        {
          "inflectionType": "22e",
          "code": "PlP",
          "morphValue": "mitmuse osastav",
          "value": "selgrooge,selgroogusid"
        },
        {
          "inflectionType": "22e",
          "code": "PlIll",
          "morphValue": "mitmuse sisseütlev",
          "value": "selgroogudesse"
        },
        {
          "inflectionType": "22e",
          "code": "PlIn",
          "morphValue": "mitmuse seesütlev",
          "value": "selgroogudes"
        },
        {
          "inflectionType": "22e",
          "code": "PlEl",
          "morphValue": "mitmuse seestütlev",
          "value": "selgroogudest"
        },
        {
          "inflectionType": "22e",
          "code": "PlAll",
          "morphValue": "mitmuse alaleütlev",
          "value": "selgroogudele"
        },
        {
          "inflectionType": "22e",
          "code": "PlAd",
          "morphValue": "mitmuse alalütlev",
          "value": "selgroogudel"
        },
        {
          "inflectionType": "22e",
          "code": "PlAbl",
          "morphValue": "mitmuse alaltütlev",
          "value": "selgroogudelt"
        },
        {
          "inflectionType": "22e",
          "code": "PlTr",
          "morphValue": "mitmuse saav",
          "value": "selgroogudeks"
        },
        {
          "inflectionType": "22e",
          "code": "PlTer",
          "morphValue": "mitmuse rajav",
          "value": "selgroogudeni"
        },
        {
          "inflectionType": "22e",
          "code": "PlEs",
          "morphValue": "mitmuse olev",
          "value": "selgroogudena"
        },
        {
          "inflectionType": "22e",
          "code": "PlAb",
          "morphValue": "mitmuse ilmaütlev",
          "value": "selgroogudeta"
        },
        {
          "inflectionType": "22e",
          "code": "PlKom",
          "morphValue": "mitmuse kaasaütlev",
          "value": "selgroogudega"
        }
      ],
      "meanings": [
        {
          "definition": "skeleti keskne osa, paljudest lülidest koosnev inimese jt selgroogsete keha põhitugi,rida väikseid omavahel ühendatud luid selja keskel",
          "partOfSpeech": [
            {
              "code": "s",
              "value": "nimisõna, substantiiv"
            }
          ],
          "examples": [
            "Jaanalinnu jalahoop võib purustada lõvi selgroo.",
            "Sass murdis mitu luud, vigastada sai ka noormehe selgroog.",
            "Ta vigastas kukkudes selgroogu."
          ],
          "synonyms": [
            "lülisammas",
            "selgroots",
            "seljaroots",
            "seljaluu",
            "seljakont"
          ],
          "translations": {
            "fra": [
              {
                "words": "colonne vertébrale",
                "weight": 1
              }
            ],
            "lat": [
              {
                "words": "columna vertebralis",
                "weight": 1
              }
            ],
            "rus": [
              {
                "words": "позвоночник",
                "weight": 1
              },
              {
                "words": "хребет",
                "weight": 1
              },
              {
                "words": "позвоночный столб",
                "weight": 1
              },
              {
                "words": "спинной хребет",
                "weight": 1
              },
              {
                "words": "хребтина",
                "weight": 1
              }
            ],
            "ukr": [
              {
                "words": "хребет",
                "weight": 1
              }
            ]
          }
        },
        {
          "definition": "inimese iseloomukindlus, visadus",
          "partOfSpeech": [
            {
              "code": "s",
              "value": "nimisõna, substantiiv"
            }
          ],
          "examples": [
            "Kas tal jätkub mehisust ja selgroogu?",
            "Pehme selgrooga otsustajad.",
            "Näitasime selgroogu ja marssisime saalist välja."
          ],
          "synonyms": [
            "tahtejõud",
            "tahtekindlus",
            "iseloomukindlus"
          ],
          "translations": {
            "rus": [
              {
                "words": "твёрдый характер",
                "weight": 1
              },
              {
                "words": "нравственный стержень",
                "weight": 1
              },
              {
                "words": "сила воли",
                "weight": 0.7
              },
              {
                "words": "твёрдость воли",
                "weight": 0.7
              },
              {
                "words": "постоянство характера,выдержанность характера,твёрдость характера",
                "weight": 0.7
              }
            ]
          }
        },
        {
          "definition": "keskne, kooshoidev osa või jõud",
          "partOfSpeech": [
            {
              "code": "s",
              "value": "nimisõna, substantiiv"
            }
          ],
          "examples": [
            "Võrukeste kultuuri selgroog on püsinud suulises kõnes.",
            "Haiguse selgroog oli murtud."
          ],
          "synonyms": [
            "alustugi,tala,tugisammas,alussammas,alustala",
            "liim",
            "skelett",
            "luustik"
          ],
          "translations": {
            "rus": [
              {
                "words": "стержень",
                "weight": 1
              },
              {
                "words": "костяк",
                "weight": 1
              },
              {
                "words": "основа",
                "weight": 1
              },
              {
                "words": "опора,устои,столп",
                "weight": 0.9
              },
              {
                "words": "костяк,хребет",
                "weight": 0.75
              }
            ]
          }
        }
      ],
      "similarWords": [
        "iseloomukindlus",
        "tahtekindlus",
        "tahtejõud",
        "lülisammas",
        "peajoon",
        "pealiin",
        "roots",
        "telg",
        "peatelg",
        "seljaroots",
        "selgroots",
        "seljaluu",
        "põhitelg",
        "alustugi",
        "karkass",
        "skelett",
        "luustik",
        "toes",
        "tuumik",
        "selgroogne",
        "selgroolüli",
        "selgroogsed",
        "välisskelett",
        "selgrootus",
        "selgrookanal",
        "selgrootu",
        "roots"
      ]
    }
  ],
  "translations": [
    {
      "from": "et",
      "to": "en",
      "input": "selgroog",
      "translations": [
        "backbone",
        "spine",
        "spinebone",
        "vertebral column"
      ]
    }
  ]
}