{
  "requestedWord": "katki minema",
  "estonianWord": "katki minema",
  "searchResult": [
    {
      "wordClasses": [
        "verb"
      ],
      "wordForms": [
        {
          "inflectionType": "36",
          "code": "Sup",
          "morphValue": "ma-infinitiiv e ma-tegevusnimi",
          "value": "katki minema"
        },
        {
          "inflectionType": "36",
          "code": "SupAb",
          "morphValue": "mata-vorm",
          "value": "katki minemata"
        },
        {
          "inflectionType": "36",
          "code": "SupIn",
          "morphValue": "mas-vorm",
          "value": "katki minemas"
        },
        {
          "inflectionType": "36",
          "code": "SupEl",
          "morphValue": "mast-vorm",
          "value": "katki minemast"
        },
        {
          "inflectionType": "36",
          "code": "SupTr",
          "morphValue": "maks-vorm",
          "value": "katki minemaks"
        },
        {
          "inflectionType": "36",
          "code": "SupIps",
          "morphValue": "ma-tegevusnime umbisikuline tegumood",
          "value": "katki mindama"
        },
        {
          "inflectionType": "36",
          "code": "Inf",
          "morphValue": "da-infinitiiv e da-tegevusnimi",
          "value": "katki minna"
        },
        {
          "inflectionType": "36",
          "code": "Ger",
          "morphValue": "des-vorm",
          "value": "katki minnes"
        },
        {
          "inflectionType": "36",
          "code": "PtsPrPs",
          "morphValue": "oleviku isikuline kesksõna e v-kesksõna",
          "value": "katki minev"
        },
        {
          "inflectionType": "36",
          "code": "PtsPrIps",
          "morphValue": "oleviku umbisikuline kesksõna e tav-kesksõna",
          "value": "katki mindav"
        },
        {
          "inflectionType": "36",
          "code": "PtsPtPs",
          "morphValue": "mineviku isikuline kesksõna e nud-kesksõna",
          "value": "katki läinud"
        },
        {
          "inflectionType": "36",
          "code": "PtsPtPsNeg",
          "morphValue": "mitmeosalise verbi pööratud ja eitatud nud-kesksõna",
          "value": "läinud katki"
        },
        {
          "inflectionType": "36",
          "code": "PtsPtIps",
          "morphValue": "mineviku umbisikuline kesksõna e tud-kesksõna",
          "value": "katki mindud"
        },
        {
          "inflectionType": "36",
          "code": "PtsPtIpsNeg",
          "morphValue": "mitmeosalise verbi pööratud ja eitatud tud-kesksõna",
          "value": "mindud katki"
        },
        {
          "inflectionType": "36",
          "code": "IndPrSg1",
          "morphValue": "kindla kõneviisi oleviku ainsuse 1.pööre",
          "value": "lähen katki"
        },
        {
          "inflectionType": "36",
          "code": "IndPrSg2",
          "morphValue": "kindla kõneviisi oleviku ainsuse 2.p.",
          "value": "lähed katki"
        },
        {
          "inflectionType": "36",
          "code": "IndPrSg3",
          "morphValue": "kindla kõneviisi oleviku ainsuse 3.p.",
          "value": "läheb katki"
        },
        {
          "inflectionType": "36",
          "code": "IndPrPl1",
          "morphValue": "kindla kõneviisi oleviku mitmuse 1.p.",
          "value": "läheme katki,lähme katki"
        },
        {
          "inflectionType": "36",
          "code": "IndPrPl2",
          "morphValue": "kindla kõneviisi oleviku mitmuse 2.p.",
          "value": "lähete katki"
        },
        {
          "inflectionType": "36",
          "code": "IndPrPl3",
          "morphValue": "kindla kõneviisi oleviku mitmuse 3.p.",
          "value": "lähevad katki"
        },
        {
          "inflectionType": "36",
          "code": "IndPrPs_",
          "morphValue": "kindla kõneviisi oleviku isikuline tegumood (eitusega)",
          "value": "lähe katki"
        },
        {
          "inflectionType": "36",
          "code": "IndPrIps",
          "morphValue": "kindla kõneviisi oleviku umbisikuline tegumood",
          "value": "minnakse katki"
        },
        {
          "inflectionType": "36",
          "code": "IndPrIps_",
          "morphValue": "kindla kõneviisi oleviku umbisikuline tegumood (eitusega)",
          "value": "minda katki"
        },
        {
          "inflectionType": "36",
          "code": "IndIpfSg1",
          "morphValue": "kindla kõneviisi lihtmineviku ainsuse 1.p.",
          "value": "läksin katki"
        },
        {
          "inflectionType": "36",
          "code": "IndIpfSg2",
          "morphValue": "kindla kõneviisi lihtmineviku ainsuse 2.p.",
          "value": "läksid katki"
        },
        {
          "inflectionType": "36",
          "code": "IndIpfSg3",
          "morphValue": "kindla kõneviisi lihtmineviku ainsuse 3.p.",
          "value": "läks katki"
        },
        {
          "inflectionType": "36",
          "code": "IndIpfPl1",
          "morphValue": "kindla kõneviisi lihtmineviku mitmuse 1.p.",
          "value": "läksime katki"
        },
        {
          "inflectionType": "36",
          "code": "IndIpfPl2",
          "morphValue": "kindla kõneviisi lihtmineviku mitmuse 2.p.",
          "value": "läksite katki"
        },
        {
          "inflectionType": "36",
          "code": "IndIpfPl3",
          "morphValue": "kindla kõneviisi lihtmineviku mitmuse 3.p.",
          "value": "läksid katki"
        },
        {
          "inflectionType": "36",
          "code": "IndIpfIps",
          "morphValue": "kindla kõneviisi lihtmineviku umbisikuline tegumood",
          "value": "mindi katki"
        },
        {
          "inflectionType": "36",
          "code": "KndPrSg1",
          "morphValue": "tingiva kõneviisi oleviku ainsuse 1.p.",
          "value": "läheksin katki"
        },
        {
          "inflectionType": "36",
          "code": "KndPrSg2",
          "morphValue": "tingiva kõneviisi oleviku ainsuse 2.p.",
          "value": "läheksid katki"
        },
        {
          "inflectionType": "36",
          "code": "KndPrPs",
          "morphValue": "tingiva kõneviisi oleviku isikuline tegumood",
          "value": "läheks katki"
        },
        {
          "inflectionType": "36",
          "code": "KndPrPl1",
          "morphValue": "tingiva kõneviisi oleviku mitmuse 1.p.",
          "value": "läheksime katki"
        },
        {
          "inflectionType": "36",
          "code": "KndPrPl2",
          "morphValue": "tingiva kõneviisi oleviku mitmuse 2.p.",
          "value": "läheksite katki"
        },
        {
          "inflectionType": "36",
          "code": "KndPrPl3",
          "morphValue": "tingiva kõneviisi oleviku mitmuse 3.p.",
          "value": "läheksid katki"
        },
        {
          "inflectionType": "36",
          "code": "KndPrIps",
          "morphValue": "tingiva kõneviisi oleviku umbisikuline tegumood",
          "value": "mindaks katki"
        },
        {
          "inflectionType": "36",
          "code": "KndPtSg1",
          "morphValue": "tingiva kõneviisi mineviku ainsuse 1.p.",
          "value": "läinuksin katki"
        },
        {
          "inflectionType": "36",
          "code": "KndPtSg2",
          "morphValue": "tingiva kõneviisi mineviku ainsuse 2.p.",
          "value": "läinuksid katki"
        },
        {
          "inflectionType": "36",
          "code": "KndPtPs",
          "morphValue": "tingiva kõneviisi mineviku isikuline tegumood",
          "value": "läinuks katki"
        },
        {
          "inflectionType": "36",
          "code": "KndPtPl1",
          "morphValue": "tingiva kõneviisi mineviku mitmuse 1.p.",
          "value": "läinuksime katki"
        },
        {
          "inflectionType": "36",
          "code": "KndPtPl2",
          "morphValue": "tingiva kõneviisi mineviku mitmuse 2.p.",
          "value": "läinuksite katki"
        },
        {
          "inflectionType": "36",
          "code": "KndPtPl3",
          "morphValue": "tingiva kõneviisi mineviku mitmuse 3.p.",
          "value": "läinuksid katki"
        },
        {
          "inflectionType": "36",
          "code": "KndPtIps",
          "morphValue": "tingiva kõneviisi mineviku umbisikuline tegumood",
          "value": "minduks katki"
        },
        {
          "inflectionType": "36",
          "code": "KvtPrPs",
          "morphValue": "kaudse kõneviisi oleviku isikuline tegumood",
          "value": "minevat katki"
        },
        {
          "inflectionType": "36",
          "code": "KvtPrIps",
          "morphValue": "kaudse kõneviisi oleviku umbisikuline tegumood",
          "value": "mindavat katki"
        },
        {
          "inflectionType": "36",
          "code": "KvtPtPs",
          "morphValue": "kaudse kõneviisi mineviku isikuline tegumood",
          "value": "läinuvat katki"
        },
        {
          "inflectionType": "36",
          "code": "KvtPtIps",
          "morphValue": "kaudse kõneviisi mineviku umbisikuline tegumood",
          "value": "minduvat katki"
        },
        {
          "inflectionType": "36",
          "code": "ImpPrSg2",
          "morphValue": "käskiva kõneviisi oleviku ainsuse 2.p.",
          "value": "mine katki"
        },
        {
          "inflectionType": "36",
          "code": "ImpPrPl1",
          "morphValue": "käskiva kõneviisi oleviku mitmuse 1.p.",
          "value": "mingem katki,läki katki"
        },
        {
          "inflectionType": "36",
          "code": "ImpPrPl2",
          "morphValue": "käskiva kõneviisi oleviku mitmuse 2.p.",
          "value": "minge katki"
        },
        {
          "inflectionType": "36",
          "code": "ImpPrPs",
          "morphValue": "käskiva kõneviisi oleviku isikuline tegumood",
          "value": "mingu katki"
        },
        {
          "inflectionType": "36",
          "code": "ImpPrIps",
          "morphValue": "käskiva kõneviisi oleviku umbisikuline tegumood",
          "value": "mindagu katki"
        }
      ],
      "meanings": [
        {
          "definition": "purunema, tükkideks, kildudeks minema,(seeläbi) kasutamiskõlbmatuks muutuma, töötamast, toimimast lakkama,kui miski <eki-highlight>läheb katki</eki-highlight>, siis see enam ei tööta või seda ei saa enam kasutada",
          "partOfSpeech": [
            {
              "code": "v",
              "value": "tegusõna, verb"
            }
          ],
          "examples": [
            "Vaata ette, jää võib katki minna!",
            "Kui kell katki läks, viskasin selle ära.",
            "Jalaluu läks kolmest kohast katki.",
            "Buss läks katki.",
            "Klaas läheb väga kergesti katki."
          ],
          "synonyms": [
            "purunema",
            "katkema",
            "murduma",
            "kokku kukkuma,kokku varisema,kokku langema",
            "lõhkema",
            "lõhki minema",
            "pooleks minema",
            "närustuma,räbalduma",
            "pragunema",
            "üles ütlema",
            "kuluma",
            "lagunema",
            "puruks minema"
          ],
          "translations": {
            "rus": [
              {
                "words": "ломаться",
                "weight": 1
              },
              {
                "words": "сломаться",
                "weight": 1
              },
              {
                "words": "разбиваться",
                "weight": 1
              },
              {
                "words": "разбиться",
                "weight": 1
              },
              {
                "words": "разваливаться,ломаться,разбиваться,разрушаться,рассыпаться,треснуть,трескать,лопнуть,разорваться,разрываться,расколоться,сломаться,рассыпаться,разлететься,разлетаться,разломаться,развалиться,рушиться,разбиться,разрушиться,биться,разламываться,раскалываться",
                "weight": 0.9
              },
              {
                "words": "рваться,обрываться,оборваться,разорваться,порваться",
                "weight": 0.9
              },
              {
                "words": "переламываться,разламываться,ломаться,дробиться,ломиться,сломаться,проламываться,проломиться,обламываться,обломиться,сламываться,сломиться,поломаться,переломиться,отламываться,отломиться,обломаться,раздробиться",
                "weight": 0.9
              },
              {
                "words": "обваливаться,обвалиться,обрушиться,рухнуть,рушиться,разваливаться,развалиться",
                "weight": 0.9
              },
              {
                "words": "трескаться,растрескаться,лопаться,растрескиваться,потрескаться,лопнуть",
                "weight": 0.9
              },
              {
                "words": "раскалываться,разорваться,разрываться,лопаться,лопнуть,расколоться",
                "weight": 0.9
              },
              {
                "words": "истрепаться,обтрёпываться,обтрепаться,рваться,разорваться,разрываться,изорваться,затрепаться,износиться в лохмотья,истрёпываться,изнашиваться в лохмотья,обноситься,обнашиваться,трепаться",
                "weight": 0.9
              },
              {
                "words": "истрескаться,давать трещину,потрескаться,трескаться,растрескаться,поколоться,дать трещину,треснуть,надтреснуть,растрескиваться,истрескиваться",
                "weight": 0.9
              },
              {
                "words": "сдавать,отказывать,отказать,сдать,портиться,испортиться",
                "weight": 0.7
              },
              {
                "words": "истираться,продырявиться,продырявливаться,истаскаться,истаскиваться,сноситься,снашиваться,износиться,изнашиваться,протереться,протираться,истереться",
                "weight": 0.9
              },
              {
                "words": "разломаться,разламываться,развалиться,разваливаться,разрушиться,разрушаться",
                "weight": 0.7
              },
              {
                "words": "разорваться,разбиться",
                "weight": 0.7
              }
            ],
            "ukr": [
              {
                "words": "ламатися",
                "weight": 1
              },
              {
                "words": "зламатися",
                "weight": 1
              },
              {
                "words": "поламатися",
                "weight": 1
              },
              {
                "words": "розбиватися",
                "weight": 1
              },
              {
                "words": "розбитися",
                "weight": 1
              },
              {
                "words": "розбитися,розбиватися,битися",
                "weight": 0.9
              },
              {
                "words": "переламуватися,ламатися,ломитися,зламатися,переламатися,переломлюватися,переломитися,розламуватися,розламатися",
                "weight": 0.9
              },
              {
                "words": "протертися,протиратися,зноситися,зношуватися",
                "weight": 0.9
              },
              {
                "words": "розломитися,розламуватися,розвалитися,розвалюватися,зруйнуватися,руйнуватися",
                "weight": 0.7
              }
            ],
            "fra": [
              {
                "words": "se briser,se casser",
                "weight": 0.9
              },
              {
                "words": "se briser,se casser",
                "weight": 0.9
              },
              {
                "words": "s'user",
                "weight": 0.9
              },
              {
                "words": "éclater,se disloquer,se désagréger,se décomposer,se fragmenter",
                "weight": 0.7
              }
            ]
          }
        },
        {
          "definition": "(suhete, seisundite vms kohta:) otsa lõppema, olemast lakkama,(hingelise murdumise kohta)",
          "partOfSpeech": [
            {
              "code": "v",
              "value": "tegusõna, verb"
            }
          ],
          "examples": [
            "Suhted lähevad katki, sest üksteisega ei räägita.",
            "Kohtudes eksmehe uue naisega, läksin taas katki."
          ],
          "synonyms": [
            "purunema",
            "murduma",
            "kokku varisema,kokku kukkuma",
            "kokku varisema,kokku kukkuma",
            "lõhki minema",
            "hingusele minema",
            "katkema",
            "lagunema"
          ],
          "translations": {
            "rus": [
              {
                "words": "рваться",
                "weight": 1
              },
              {
                "words": "разбиться,разлететься,разлетаться,рушиться,рухнуть,разрушаться,разрушиться,разбиваться",
                "weight": 0.9
              },
              {
                "words": "надламываться,надломиться,сломаться,сламываться,сломиться",
                "weight": 0.9
              },
              {
                "words": "разрушаться,рушиться,рухнуть,разрушиться",
                "weight": 0.9
              },
              {
                "words": "свалиться с ног,падать с ног,протянуть ноги,валиться с ног",
                "weight": 0.9
              },
              {
                "words": "перестать действовать,перестать существовать,переставать существовать,переставать действовать",
                "weight": 0.7
              },
              {
                "words": "прекратиться,прекращаться",
                "weight": 0.9
              },
              {
                "words": "распасться,распадаться",
                "weight": 0.7
              }
            ]
          }
        }
      ],
      "similarWords": [
        "pooleks minema",
        "nurja minema",
        "käest ära minema",
        "hukka minema",
        "hingusele minema",
        "hapuks minema",
        "aia taha minema",
        "purunema",
        "katkema",
        "murduma",
        "kokku varisema",
        "räbalduma",
        "lõhki minema",
        "lõhkema",
        "pragunema",
        "kuluma",
        "hävima",
        "rikki",
        "korrast ära"
      ]
    }
  ],
  "translations": [
    {
      "from": "et",
      "to": "en",
      "input": "katki minema",
      "translations": [
        "break down"
      ]
    }
  ]
}